federatedTenantAuthAPI/__init__.py
federatedTenantAuthAPI/get.py
TapisFederatedAuthClientAPI-0.0.1.dist-info/LICENSE
TapisFederatedAuthClientAPI-0.0.1.dist-info/METADATA
TapisFederatedAuthClientAPI-0.0.1.dist-info/WHEEL
TapisFederatedAuthClientAPI-0.0.1.dist-info/top_level.txt
TapisFederatedAuthClientAPI-0.0.1.dist-info/RECORD
