Metadata-Version: 2.1
Name: TapisFederatedAuthClientAPI
Version: 0.0.1
Summary: Lightweight API to retrieve authenticator clients for Tapis tenants
Author-email: Michael Ray <m.ray37990@gmail.com>
License: GNU GENERAL PUBLIC LICENSE
Project-URL: Homepage, https://github.com/sdsc-hpc-training-org/hello_icicle_auth_clients/tree/main/icicle_rel_03_2023/FederatedAuth
Keywords: Tapis,CLI,Agave,HPC,Tapis Pods,TACC
Classifier: License :: OSI Approved :: GNU General Public License (GPL)
Classifier: Programming Language :: Python
Classifier: Programming Language :: Python :: 3
Requires-Python: >=3.9
License-File: LICENSE
Requires-Dist: requests
Provides-Extra: dev
